pyflocker-0.4.2.dist-info/METADATA
pyflocker-0.4.2.dist-info/WHEEL
pyflocker-0.4.2.dist-info/licenses/LICENSE
pyflocker/__init__.py
pyflocker/_version.py
pyflocker/ciphers/__init__.py
pyflocker/ciphers/backends/__init__.py
pyflocker/ciphers/backends/asymmetric.py
pyflocker/ciphers/backends/cryptodome_/AES.py
pyflocker/ciphers/backends/cryptodome_/ChaCha20.py
pyflocker/ciphers/backends/cryptodome_/ECC.py
pyflocker/ciphers/backends/cryptodome_/Hash.py
pyflocker/ciphers/backends/cryptodome_/RSA.py
pyflocker/ciphers/backends/cryptodome_/__init__.py
pyflocker/ciphers/backends/cryptodome_/asymmetric.py
pyflocker/ciphers/backends/cryptodome_/misc.py
pyflocker/ciphers/backends/cryptodome_/symmetric.py
pyflocker/ciphers/backends/cryptography_/AES.py
pyflocker/ciphers/backends/cryptography_/Camellia.py
pyflocker/ciphers/backends/cryptography_/ChaCha20.py
pyflocker/ciphers/backends/cryptography_/DH.py
pyflocker/ciphers/backends/cryptography_/ECC.py
pyflocker/ciphers/backends/cryptography_/Hash.py
pyflocker/ciphers/backends/cryptography_/RSA.py
pyflocker/ciphers/backends/cryptography_/__init__.py
pyflocker/ciphers/backends/cryptography_/asymmetric.py
pyflocker/ciphers/backends/cryptography_/misc.py
pyflocker/ciphers/backends/cryptography_/symmetric.py
pyflocker/ciphers/backends/symmetric.py
pyflocker/ciphers/base.py
pyflocker/ciphers/exc.py
pyflocker/ciphers/interfaces/AES.py
pyflocker/ciphers/interfaces/Camellia.py
pyflocker/ciphers/interfaces/ChaCha20.py
pyflocker/ciphers/interfaces/DH.py
pyflocker/ciphers/interfaces/ECC.py
pyflocker/ciphers/interfaces/Hash.py
pyflocker/ciphers/interfaces/RSA.py
pyflocker/ciphers/interfaces/__init__.py
pyflocker/ciphers/modes.py
pyflocker/locker.py
pyflocker/py.typed
pyflocker-0.4.2.dist-info/RECORD
