Metadata-Version: 2.1
Name: PyFLocker
Version: 0.4.2
Summary: Python Cryptographic (File Locking) Library
Keywords: cryptography,encryption,python,pypi,symmetric key,asymmetric key,aes,chacha20,camellia,rsa,dsa,ecc,file encryption,secure communication,cryptography library
Author-Email: Arunanshu Biswas <mydellpc07@gmail.com>
License: MIT
Classifier: Programming Language :: Python :: 3
Classifier: Programming Language :: Python :: 3.8
Classifier: Programming Language :: Python :: 3.9
Classifier: Programming Language :: Python :: 3.10
Classifier: Programming Language :: Python :: 3.11
Classifier: Programming Language :: Python :: 3.12
Classifier: License :: OSI Approved :: MIT License
Classifier: Operating System :: OS Independent
Classifier: Intended Audience :: Developers
Classifier: Topic :: Security :: Cryptography
Project-URL: Bug tracker, https://github.com/arunanshub/pyflocker/issues
Project-URL: Changelog, https://github.com/arunanshub/pyflocker/blob/master/CHANGELOG.md
Project-URL: Documentation, https://pyflocker.readthedocs.io
Project-URL: Repository, https://github.com/arunanshub/pyflocker
Requires-Python: >=3.9
Requires-Dist: pycryptodomex>=3.9.8
Requires-Dist: cryptography[ssh]!=37.0.0,>=35.0.0
